devseclint/__init__.py
devseclint/remediator.py
devseclint/scanner.py
devseclint/utils.py
devseclint/rules/__init__.py
devseclint/rules/docker_rules.py
devseclint/rules/env_rules.py
devseclint/rules/k8s_rules.py
devseclint-0.1.0.dist-info/METADATA
devseclint-0.1.0.dist-info/WHEEL
devseclint-0.1.0.dist-info/entry_points.txt
devseclint-0.1.0.dist-info/top_level.txt
devseclint-0.1.0.dist-info/RECORD
