Metadata-Version: 2.4
Name: devseclint
Version: 0.1.0
Summary: Scan development configs for security misconfigurations
Author-email: Rohan Shaw <rohanshaw.dev@gmail.com>
License: MIT
Requires-Python: >=3.8
Requires-Dist: typer[all]
Requires-Dist: pyyaml
Requires-Dist: rich
Requires-Dist: google-generativeai
Requires-Dist: python-dotenv
